socialmagic/__init__.py
socialmagic/emojify.py
socialmagic/fakebuster.py
socialmagic/storygen.py
social_magic-0.1.0.dist-info/METADATA
social_magic-0.1.0.dist-info/WHEEL
social_magic-0.1.0.dist-info/top_level.txt
social_magic-0.1.0.dist-info/RECORD
