Metadata-Version: 2.4
Name: social-magic
Version: 0.1.0
Summary: A Python library for social media content enhancement
Home-page: https://github.com/socialmagic/social-magic
Author: SocialMagic Team
Author-email: SocialMagic Team <contact@socialmagic.dev>
Project-URL: Homepage, https://github.com/socialmagic/social-magic
Project-URL: Bug Reports, https://github.com/socialmagic/social-magic/issues
Project-URL: Source, https://github.com/socialmagic/social-magic
Project-URL: Documentation, https://github.com/socialmagic/social-magic#readme
Keywords: sentiment analysis,image detection,story generation,social media
Classifier: Development Status :: 3 - Alpha
Classifier: Intended Audience :: Developers
Classifier: License :: OSI Approved :: MIT License
Classifier: Operating System :: OS Independent
Classifier: Programming Language :: Python :: 3
Classifier: Programming Language :: Python :: 3.7
Classifier: Programming Language :: Python :: 3.8
Classifier: Programming Language :: Python :: 3.9
Classifier: Programming Language :: Python :: 3.10
Classifier: Programming Language :: Python :: 3.11
Classifier: Programming Language :: Python :: 3.12
Classifier: Topic :: Software Development :: Libraries :: Python Modules
Classifier: Topic :: Text Processing :: Linguistic
Classifier: Topic :: Multimedia :: Graphics
Classifier: Topic :: Internet :: WWW/HTTP :: Dynamic Content
Requires-Python: >=3.7
Requires-Dist: vaderSentiment>=3.3.0
Requires-Dist: emoji>=2.0.0
Requires-Dist: Pillow>=8.0.0
Requires-Dist: imagehash>=4.3.0
Dynamic: author
Dynamic: home-page
Dynamic: requires-python
